virtual_camera/__init__.py
virtual_camera/virtual_camera.py
virtual_camera/data/calibration.yml
virtual_camera/data/dst_image.jpg
virtual_camera/data/mask.png
virtual_camera/data/src_image.jpg
virtual_camera-1.0.3.dist-info/METADATA
virtual_camera-1.0.3.dist-info/WHEEL
virtual_camera-1.0.3.dist-info/top_level.txt
virtual_camera-1.0.3.dist-info/RECORD
