Metadata-Version: 2.1
Name: virtual-camera
Version: 1.0.3
Summary: Virtual Camera
Home-page: https://github.com/AlphaLFC/virtual_camera
Author: AlphaLFC
Author-email: alphali@motovis.com
License: UNKNOWN
Platform: UNKNOWN
Requires-Dist: numpy
Requires-Dist: scipy
